treepick/__init__.py
treepick/__main__.py
treepick/color.py
treepick/du.py
treepick/keys.py
treepick/paths.py
treepick/pick.py
treepick/treepick.py
treepick-0.1.4.dist-info/METADATA
treepick-0.1.4.dist-info/RECORD
treepick-0.1.4.dist-info/WHEEL
treepick-0.1.4.dist-info/entry_points.txt
treepick-0.1.4.dist-info/top_level.txt
