Metadata-Version: 2.1
Name: treepick
Version: 0.1.4
Summary: Curses Tree Style Path Picker
Home-page: https://github.com/tslight/treepick
Author: Toby Slight
Author-email: tobyslight@gmail.com
License: UNKNOWN
Platform: UNKNOWN
Classifier: Programming Language :: Python :: 3
Classifier: License :: OSI Approved :: ISC License (ISCL)
Classifier: Operating System :: OS Independent
